pyclts/__init__.py
pyclts/__main__.py
pyclts/api.py
pyclts/consonants.html
pyclts/inventories.py
pyclts/ipachart.py
pyclts/models.py
pyclts/np_consonants.html
pyclts/soundclasses.py
pyclts/transcriptiondata.py
pyclts/transcriptionsystem.py
pyclts/util.py
pyclts/vowels.svg
pyclts/commands/__init__.py
pyclts/commands/dist.py
pyclts/commands/features.py
pyclts/commands/ls.py
pyclts/commands/make_app.py
pyclts/commands/make_dataset.py
pyclts/commands/make_pkg.py
pyclts/commands/map.py
pyclts/commands/sounds.py
pyclts/commands/stats.py
pyclts/commands/table.py
pyclts/commands/tdstats.py
pyclts/commands/test.py
pyclts/commands/test_dataset.py
pyclts/data/clicks.tsv
pyclts/data/test_data.tsv
pyclts-3.2.0.dist-info/LICENSE
pyclts-3.2.0.dist-info/METADATA
pyclts-3.2.0.dist-info/WHEEL
pyclts-3.2.0.dist-info/entry_points.txt
pyclts-3.2.0.dist-info/top_level.txt
pyclts-3.2.0.dist-info/RECORD
