Metadata-Version: 2.1
Name: pyclts
Version: 3.2.0
Summary: Programmatic access to CLTS
Home-page: https://github.com/cldf-clts/pyclts
Author: Johann-Mattis List, Cormac Anderson, Tiago Tresoldi, and Robert Forkel
Author-email: mattis.list@lingpy.org
License: Apache 2.0
Project-URL: Bug Tracker, https://github.com/cldf-clts/pyclts/issues
Keywords: linguistics
Platform: any
Classifier: Development Status :: 5 - Production/Stable
Classifier: Intended Audience :: Developers
Classifier: Intended Audience :: Science/Research
Classifier: Natural Language :: English
Classifier: Operating System :: OS Independent
Classifier: Programming Language :: Python :: 3
Classifier: Programming Language :: Python :: 3.8
Classifier: Programming Language :: Python :: 3.9
Classifier: Programming Language :: Python :: 3.10
Classifier: Programming Language :: Python :: 3.11
Classifier: Programming Language :: Python :: 3.12
Classifier: Programming Language :: Python :: Implementation :: CPython
Classifier: Programming Language :: Python :: Implementation :: PyPy
Classifier: License :: OSI Approved :: Apache Software License
Requires-Python: >=3.8
Provides-Extra: dev
Provides-Extra: test
License-File: LICENSE
